dsci_310_group_11_pkg/__init__.py
dsci_310_group_11_pkg/grapher.py
dsci_310_group_11_pkg/optimize.py
dsci_310_group_11_pkg/pipeline.py
dsci_310_group_11_pkg/preprocess.py
dsci_310_group_11_pkg-0.1.1.dist-info/LICENSE
dsci_310_group_11_pkg-0.1.1.dist-info/METADATA
dsci_310_group_11_pkg-0.1.1.dist-info/WHEEL
dsci_310_group_11_pkg-0.1.1.dist-info/RECORD
