Metadata-Version: 2.1
Name: dsci-310-group-11-pkg
Version: 0.1.1
Summary: package for dsci310 report
License: MIT
Author: Anthony Huang
Requires-Python: >=3.10,<4.0
Classifier: License :: OSI Approved :: MIT License
Classifier: Programming Language :: Python :: 3
Classifier: Programming Language :: Python :: 3.10
Classifier: Programming Language :: Python :: 3.11
Requires-Dist: altair (>=4.2.2,<5.0.0)
Requires-Dist: argparse (>=1.4.0,<2.0.0)
Requires-Dist: matplotlib (>=3.7.1,<4.0.0)
Requires-Dist: numpy (>=1.24.2,<2.0.0)
Requires-Dist: pandas (>=2.0.0,<3.0.0)
Requires-Dist: pytest (>=7.3.0,<8.0.0)
Requires-Dist: requests (>=2.28.2,<3.0.0)
Requires-Dist: scikit-learn (>=1.2.2,<2.0.0)
Requires-Dist: seaborn (>=0.12.2,<0.13.0)
